odoo9_addon_stock_picking_delivery_rate-9.0.1.0.0-py2.7-nspkg.pth
odoo_addons/stock_picking_delivery_rate/__openerp__.py
odoo_addons/stock_picking_delivery_rate/__init__.py
odoo_addons/stock_picking_delivery_rate/README.rst
odoo_addons/stock_picking_delivery_rate/security/ir.model.access.csv
odoo_addons/stock_picking_delivery_rate/models/stock_picking_rate.py
odoo_addons/stock_picking_delivery_rate/models/__init__.py
odoo_addons/stock_picking_delivery_rate/models/stock_picking.py
odoo_addons/stock_picking_delivery_rate/views/stock_picking_rate_view.xml
odoo_addons/stock_picking_delivery_rate/views/stock_picking_view.xml
odoo_addons/stock_picking_delivery_rate/wizards/__init__.py
odoo_addons/stock_picking_delivery_rate/wizards/stock_picking_rate_purchase.py
odoo_addons/stock_picking_delivery_rate/wizards/stock_picking_rate_purchase_view.xml
odoo_addons/stock_picking_delivery_rate/tests/test_stock_picking_rate_purchase.py
odoo_addons/stock_picking_delivery_rate/tests/test_stock_picking_rate.py
odoo_addons/stock_picking_delivery_rate/tests/__init__.py
odoo_addons/stock_picking_delivery_rate/tests/common.py
odoo_addons/stock_picking_delivery_rate/static/description/icon.png
odoo9_addon_stock_picking_delivery_rate-9.0.1.0.0.dist-info/top_level.txt
odoo9_addon_stock_picking_delivery_rate-9.0.1.0.0.dist-info/WHEEL
odoo9_addon_stock_picking_delivery_rate-9.0.1.0.0.dist-info/RECORD
odoo9_addon_stock_picking_delivery_rate-9.0.1.0.0.dist-info/metadata.json
odoo9_addon_stock_picking_delivery_rate-9.0.1.0.0.dist-info/DESCRIPTION.rst
odoo9_addon_stock_picking_delivery_rate-9.0.1.0.0.dist-info/METADATA
odoo9_addon_stock_picking_delivery_rate-9.0.1.0.0.dist-info/namespace_packages.txt
